basylic/__init__.py
basylic/client.py
basylic-0.22.0.dist-info/LICENSE
basylic-0.22.0.dist-info/METADATA
basylic-0.22.0.dist-info/WHEEL
basylic-0.22.0.dist-info/top_level.txt
basylic-0.22.0.dist-info/RECORD
