Metadata-Version: 2.1
Name: basylic
Version: 0.22.0
Summary: Python interface to Basylic's API
Home-page: https://github.com/basylic-team/basylic-python-client
Download-URL: https://github.com/basylic-team/basylic-python-client/tarball/0.22.0
Author: Petar Todorov
Author-email: ptodorov@etaonis.com
License: MIT
Keywords: insurance,anti-fraud,basylic
Classifier: Intended Audience :: Financial and Insurance Industry
Classifier: License :: OSI Approved :: MIT License
Classifier: Programming Language :: Python :: 3
License-File: LICENSE
Requires-Dist: requests (>=2.22.0)
Requires-Dist: asyncio (>=3.4.3)
